sb_cli/__init__.py
sb_cli/config.py
sb_cli/delete_run.py
sb_cli/gen_api_key.py
sb_cli/get_quotas.py
sb_cli/get_report.py
sb_cli/list_runs.py
sb_cli/submit.py
sb_cli/utils.py
sb_cli/verify_api_key.py
sb_cli-0.1.5.dist-info/METADATA
sb_cli-0.1.5.dist-info/WHEEL
sb_cli-0.1.5.dist-info/entry_points.txt
sb_cli-0.1.5.dist-info/licenses/LICENSE
sb_cli-0.1.5.dist-info/RECORD
