Metadata-Version: 2.4
Name: sb-cli
Version: 0.1.5
Summary: Submit predictions to the SWE-bench API and manage your runs
Project-URL: Homepage, https://github.com/swe-bench/sb-cli
Project-URL: Issues, https://github.com/swe-bench/sb-cli/issues
Author-email: SWE-bench team <support@swebench.com>
License: MIT
License-File: LICENSE
Classifier: License :: OSI Approved :: MIT License
Classifier: Operating System :: OS Independent
Classifier: Programming Language :: Python :: 3
Classifier: Programming Language :: Python :: 3.10
Classifier: Programming Language :: Python :: 3.11
Requires-Python: >=3.10
Requires-Dist: click<8.2.0
Requires-Dist: requests
Requires-Dist: rich
Requires-Dist: typer>=0.9.0
Provides-Extra: dev
Requires-Dist: mkdocs-material>=9.0.0; extra == 'dev'
Requires-Dist: mkdocs>=1.5.0; extra == 'dev'
